{
    "id": 144847813,
    "name": "spoony spoonicus",
    "author": "vayt1",
    "creators": [1],
    "verifier": "freyaii",
    "verification": "https://medal.tv/games/geometry-dash/clip/n84O1lww7P5n2nJ2l?invite=cr-MSxZeXUsNTg3NDU4MDcx",
    "percentToQualify": "100",
    "password": "Free To Copy",
    "enjoyment": "5.433s",
    "records": [
        {
            "user": "Sandwich",
            "link": "https://medal.tv/games/geometry-dash/clips/n8p2HMWdDWf7JhlsC?invite=cr-MSxSeEcsNDcyMzE5NTg3",
            "percent": 100,
            "hz": 0
        }
    ]
}
